prim_ctrl/__init__.py
prim_ctrl/__main__.py
prim_ctrl-0.7.13.dist-info/entry_points.txt
prim_ctrl-0.7.13.dist-info/licenses/LICENSE
prim_ctrl-0.7.13.dist-info/METADATA
prim_ctrl-0.7.13.dist-info/WHEEL
prim_ctrl-0.7.13.dist-info/RECORD
