Metadata-Version: 2.4
Name: prim-ctrl
Version: 0.7.13
Summary: Primitive Ctrl - Remote control of your phone's Primitive FTPd Android SFTP server and optionally Tailscale VPN.
License-Expression: Apache-2.0
License-File: LICENSE
Author: Laszlo Magyar
Author-email: lmagyar1973@gmail.com
Requires-Python: >=3.12, <4.0
Classifier: Development Status :: 4 - Beta
Classifier: Environment :: Console
Classifier: Operating System :: OS Independent
Requires-Dist: aiohttp (>=3.13.2)
Requires-Dist: asyncssh (>=2.21.1)
Requires-Dist: dnspython (>=2.8.0)
Requires-Dist: platformdirs (>=4.5.0)
Requires-Dist: tailscale-fixed (>=0.7.0,<0.8.0)
Requires-Dist: zeroconf (>=0.148.0)
Project-URL: Change Log, https://github.com/lmagyar/prim-ctrl/blob/main/CHANGELOG.md
